Workbook

Sheet Como usar
B2: Seu mini sistema financeiro
B3: Finanças que Curam · Grupo FQC · Comunidade Manada · Por Aline Seabra
B5: O segredo não é a planilha perfeita. É a rotina: 10 minutos por semana para lançar e olhar o painel.
B7: Como preencher
B8: 1. Na aba Lançamentos, registre cada entrada e cada gasto: data, descrição, categoria, valor, forma de pagamento e a emoção do momento.
B9: 2. A categoria define o grupo sozinha (Entrada, Fixo, Variável, Dívida ou Guardado). Para criar categorias, use a aba Categorias.
B10: 3. Na aba Metas, liste seus objetivos e quanto já guardou para cada um.
B11: 4. No Painel, troque o mês de referência para ver qualquer mês: totais, os 4 indicadores, gastos por categoria e por emoção.
B12: 5. Método ENOP·SMED: em cada gasto, responda S ou N às três perguntas (é essencial ou necessário agora? cabe no orçamento? não é postergável?). A pontuação (nº de SIM × peso da área) e a decisão aparecem sozinhas. O Painel mostra o seu Índice de Consciência.
B13: 6. Rotina sugerida: lançar no domingo à noite e olhar o painel no dia seguinte ao salário.
B15: Legenda
B16: Célula amarela = você preenche. Texto azul = valor de exemplo. Texto preto = cálculo automático, não apague.
B18: Conteúdo educativo. Não é recomendação de investimento.

Sheet Painel
B2: Painel do mês
B4: Mês de referência (use o dia 1) | C4: 46327
B6: O mês em números | C6: Valor (R$) | D6: % das entradas | G6: Gastos por emoção | H6: Valor (R$) | I6: % dos variáveis
B7: Entradas | C7: =SUMIFS(Lançamentos!$E$6:$E$605,Lançamentos!$O$6:$O$605,"Entrada",Lançamentos!$P$6:$P$605,Painel!$C$4) -> 8700 | D7: =IF($C$7>0,C7/$C$7,0) -> 1 | G7: Necessidade | H7: =SUMIFS(Lançamentos!$E$6:$E$605,Lançamentos!$G$6:$G$605,"Necessidade",Lançamentos!$P$6:$P$605,Painel!$C$4,Lançamentos!$O$6:$O$605,"Variável") -> 1790 | I7: =IF($C$9>0,H7/$C$9,0) -> 0.6026936
B8: Gastos fixos | C8: =SUMIFS(Lançamentos!$E$6:$E$605,Lançamentos!$O$6:$O$605,"Fixo",Lançamentos!$P$6:$P$605,Painel!$C$4) -> 4460 | D8: =IF($C$7>0,C8/$C$7,0) -> 0.51264368 | G8: Recompensa | H8: =SUMIFS(Lançamentos!$E$6:$E$605,Lançamentos!$G$6:$G$605,"Recompensa",Lançamentos!$P$6:$P$605,Painel!$C$4,Lançamentos!$O$6:$O$605,"Variável") -> 555 | I8: =IF($C$9>0,H8/$C$9,0) -> 0.18686869
B9: Gastos variáveis | C9: =SUMIFS(Lançamentos!$E$6:$E$605,Lançamentos!$O$6:$O$605,"Variável",Lançamentos!$P$6:$P$605,Painel!$C$4) -> 2970 | D9: =IF($C$7>0,C9/$C$7,0) -> 0.34137931 | G9: Tédio | H9: =SUMIFS(Lançamentos!$E$6:$E$605,Lançamentos!$G$6:$G$605,"Tédio",Lançamentos!$P$6:$P$605,Painel!$C$4,Lançamentos!$O$6:$O$605,"Variável") -> 0 | I9: =IF($C$9>0,H9/$C$9,0) -> 0
B10: Parcelas de dívidas | C10: =SUMIFS(Lançamentos!$E$6:$E$605,Lançamentos!$O$6:$O$605,"Dívida",Lançamentos!$P$6:$P$605,Painel!$C$4) -> 920 | D10: =IF($C$7>0,C10/$C$7,0) -> 0.10574713 | G10: Estresse | H10: =SUMIFS(Lançamentos!$E$6:$E$605,Lançamentos!$G$6:$G$605,"Estresse",Lançamentos!$P$6:$P$605,Painel!$C$4,Lançamentos!$O$6:$O$605,"Variável") -> 95 | I10: =IF($C$9>0,H10/$C$9,0) -> 0.031986532
B11: Guardado / investido | C11: =SUMIFS(Lançamentos!$E$6:$E$605,Lançamentos!$O$6:$O$605,"Guardado",Lançamentos!$P$6:$P$605,Painel!$C$4) -> 450 | D11: =IF($C$7>0,C11/$C$7,0) -> 0.051724138 | G11: Alegria | H11: =SUMIFS(Lançamentos!$E$6:$E$605,Lançamentos!$G$6:$G$605,"Alegria",Lançamentos!$P$6:$P$605,Painel!$C$4,Lançamentos!$O$6:$O$605,"Variável") -> 270 | I11: =IF($C$9>0,H11/$C$9,0) -> 0.090909091
B12: Sobra livre do mês | C12: =C7-C8-C9-C10-C11 -> -100 | D12: =IF($C$7>0,C12/$C$7,0) -> -0.011494253 | G12: Pressão social | H12: =SUMIFS(Lançamentos!$E$6:$E$605,Lançamentos!$G$6:$G$605,"Pressão social",Lançamentos!$P$6:$P$605,Painel!$C$4,Lançamentos!$O$6:$O$605,"Variável") -> 260 | I12: =IF($C$9>0,H12/$C$9,0) -> 0.087542088
G13: Gasto emocional (recompensa + tédio + estresse) | H13: =H8+H9+H10 -> 650 | I13: =IF($C$9>0,H13/$C$9,0) -> 0.21885522
B14: Seus 4 indicadores | C14: Número | D14: Situação
B15: Taxa de poupança (guardado ÷ entradas) | C15: =IF(C7>0,C11/C7,0) -> 0.051724138 | D15: =IF(C15>=0.1,"Saudável",IF(C15>0,"Atenção","Alerta")) -> Atenção | G15: Método ENOP·SMED no mês | H15: Valor (R$) | I15: Qtd.
B16: Índice de endividamento | C16: =IF(C7>0,C10/C7,0) -> 0.10574713 | D16: =IF(C16<=0.3,"Saudável",IF(C16<=0.4,"Atenção","Alerta")) -> Saudável | G16: Índice de Consciência (% com 8 pontos ou mais) | I16: =IF(COUNTIFS(Lançamentos!$L$6:$L$605,">=0",Lançamentos!$P$6:$P$605,Painel!$C$4)=0,0,COUNTIFS(Lançamentos!$L$6:$L$605,">=8",Lançamentos!$P$6:$P$605,Painel!$C$4)/COUNTIFS(Lançamentos!$L$6:$L$605,">=0",Lançamentos!$P$6:$P$605,Painel!$C$4)) -> 0.63636364
B17: Meses de reserva | C17: =IF(C8>0,N(Metas!E6)/C8,0) -> 0.89686099 | D17: =IF(C17>=6,"Saudável",IF(C17>=3,"Atenção","Alerta")) -> Alerta | G17: Executar | H17: =SUMIFS(Lançamentos!$E$6:$E$605,Lançamentos!$M$6:$M$605,"Executar",Lançamentos!$P$6:$P$605,Painel!$C$4) -> 5920 | I17: =COUNTIFS(Lançamentos!$M$6:$M$605,"Executar",Lançamentos!$P$6:$P$605,Painel!$C$4) -> 11
B18: Peso do custo fixo | C18: =IF(C7>0,C8/C7,0) -> 0.51264368 | D18: =IF(C18<=0.5,"Saudável",IF(C18<=0.65,"Atenção","Alerta")) -> Atenção | G18: Executar com controle | H18: =SUMIFS(Lançamentos!$E$6:$E$605,Lançamentos!$M$6:$M$605,"Executar com controle",Lançamentos!$P$6:$P$605,Painel!$C$4) -> 1090 | I18: =COUNTIFS(Lançamentos!$M$6:$M$605,"Executar com controle",Lançamentos!$P$6:$P$605,Painel!$C$4) -> 3
B19: Referências da Manada: poupança 10%+, endividamento até 30%, reserva de 3 a 6 meses, custo fixo até 50%. | G19: Postergar | H19: =SUMIFS(Lançamentos!$E$6:$E$605,Lançamentos!$M$6:$M$605,"Postergar",Lançamentos!$P$6:$P$605,Painel!$C$4) -> 0 | I19: =COUNTIFS(Lançamentos!$M$6:$M$605,"Postergar",Lançamentos!$P$6:$P$605,Painel!$C$4) -> 0
G20: Cancelar | H20: =SUMIFS(Lançamentos!$E$6:$E$605,Lançamentos!$M$6:$M$605,"Cancelar",Lançamentos!$P$6:$P$605,Painel!$C$4) -> 1340 | I20: =COUNTIFS(Lançamentos!$M$6:$M$605,"Cancelar",Lançamentos!$P$6:$P$605,Painel!$C$4) -> 8
B21: Alertas de execução do orçamento: 90% do limite = atenção · 100% = crítico. Limites na aba Categorias. | G21: Cancelar = sinal de gasto emocional. Nem todo gasto possível é um gasto plausível.
B22: Gastos por categoria no mês | C22: Valor (R$) | D22: % do limite | E22: Alerta
B23: =Categorias!B9 -> Moradia | C23: =SUMIFS(Lançamentos!$E$6:$E$605,Lançamentos!$D$6:$D$605,B23,Lançamentos!$P$6:$P$605,Painel!$C$4) -> 2250 | D23: =IF(N(IFERROR(INDEX(Categorias!$E$6:$E$45,MATCH(B23,Categorias!$B$6:$B$45,0)),0))>0,C23/IFERROR(INDEX(Categorias!$E$6:$E$45,MATCH(B23,Categorias!$B$6:$B$45,0)),0),"") | E23: =IF(D23="","Sem limite",IF(D23>=1,"Crítico",IF(D23>=0.9,"Atenção","OK"))) -> Sem limite
B24: =Categorias!B10 -> Contas da casa | C24: =SUMIFS(Lançamentos!$E$6:$E$605,Lançamentos!$D$6:$D$605,B24,Lançamentos!$P$6:$P$605,Painel!$C$4) -> 320 | D24: =IF(N(IFERROR(INDEX(Categorias!$E$6:$E$45,MATCH(B24,Categorias!$B$6:$B$45,0)),0))>0,C24/IFERROR(INDEX(Categorias!$E$6:$E$45,MATCH(B24,Categorias!$B$6:$B$45,0)),0),"") | E24: =IF(D24="","Sem limite",IF(D24>=1,"Crítico",IF(D24>=0.9,"Atenção","OK"))) -> Sem limite
B25: =Categorias!B11 -> Internet e celular | C25: =SUMIFS(Lançamentos!$E$6:$E$605,Lançamentos!$D$6:$D$605,B25,Lançamentos!$P$6:$P$605,Painel!$C$4) -> 180 | D25: =IF(N(IFERROR(INDEX(Categorias!$E$6:$E$45,MATCH(B25,Categorias!$B$6:$B$45,0)),0))>0,C25/IFERROR(INDEX(Categorias!$E$6:$E$45,MATCH(B25,Categorias!$B$6:$B$45,0)),0),"") | E25: =IF(D25="","Sem limite",IF(D25>=1,"Crítico",IF(D25>=0.9,"Atenção","OK"))) -> Sem limite
B26: =Categorias!B12 -> Educação | C26: =SUMIFS(Lançamentos!$E$6:$E$605,Lançamentos!$D$6:$D$605,B26,Lançamentos!$P$6:$P$605,Painel!$C$4) -> 900 | D26: =IF(N(IFERROR(INDEX(Categorias!$E$6:$E$45,MATCH(B26,Categorias!$B$6:$B$45,0)),0))>0,C26/IFERROR(INDEX(Categorias!$E$6:$E$45,MATCH(B26,Categorias!$B$6:$B$45,0)),0),"") | E26: =IF(D26="","Sem limite",IF(D26>=1,"Crítico",IF(D26>=0.9,"Atenção","OK"))) -> Sem limite
B27: =Categorias!B13 -> Saúde (plano) | C27: =SUMIFS(Lançamentos!$E$6:$E$605,Lançamentos!$D$6:$D$605,B27,Lançamentos!$P$6:$P$605,Painel!$C$4) -> 650 | D27: =IF(N(IFERROR(INDEX(Categorias!$E$6:$E$45,MATCH(B27,Categorias!$B$6:$B$45,0)),0))>0,C27/IFERROR(INDEX(Categorias!$E$6:$E$45,MATCH(B27,Categorias!$B$6:$B$45,0)),0),"") | E27: =IF(D27="","Sem limite",IF(D27>=1,"Crítico",IF(D27>=0.9,"Atenção","OK"))) -> Sem limite
B28: =Categorias!B14 -> Assinaturas | C28: =SUMIFS(Lançamentos!$E$6:$E$605,Lançamentos!$D$6:$D$605,B28,Lançamentos!$P$6:$P$605,Painel!$C$4) -> 160 | D28: =IF(N(IFERROR(INDEX(Categorias!$E$6:$E$45,MATCH(B28,Categorias!$B$6:$B$45,0)),0))>0,C28/IFERROR(INDEX(Categorias!$E$6:$E$45,MATCH(B28,Categorias!$B$6:$B$45,0)),0),"") | E28: =IF(D28="","Sem limite",IF(D28>=1,"Crítico",IF(D28>=0.9,"Atenção","OK"))) -> Sem limite
B29: =Categorias!B15 -> Mercado | C29: =SUMIFS(Lançamentos!$E$6:$E$605,Lançamentos!$D$6:$D$605,B29,Lançamentos!$P$6:$P$605,Painel!$C$4) -> 1200 | D29: =IF(N(IFERROR(INDEX(Categorias!$E$6:$E$45,MATCH(B29,Categorias!$B$6:$B$45,0)),0))>0,C29/IFERROR(INDEX(Categorias!$E$6:$E$45,MATCH(B29,Categorias!$B$6:$B$45,0)),0),"") -> 0.92307692 | E29: =IF(D29="","Sem limite",IF(D29>=1,"Crítico",IF(D29>=0.9,"Atenção","OK"))) -> Atenção
B30: =Categorias!B16 -> Delivery e restaurantes | C30: =SUMIFS(Lançamentos!$E$6:$E$605,Lançamentos!$D$6:$D$605,B30,Lançamentos!$P$6:$P$605,Painel!$C$4) -> 520 | D30: =IF(N(IFERROR(INDEX(Categorias!$E$6:$E$45,MATCH(B30,Categorias!$B$6:$B$45,0)),0))>0,C30/IFERROR(INDEX(Categorias!$E$6:$E$45,MATCH(B30,Categorias!$B$6:$B$45,0)),0),"") -> 1.3 | E30: =IF(D30="","Sem limite",IF(D30>=1,"Crítico",IF(D30>=0.9,"Atenção","OK"))) -> Crítico
B31: =Categorias!B17 -> Transporte | C31: =SUMIFS(Lançamentos!$E$6:$E$605,Lançamentos!$D$6:$D$605,B31,Lançamentos!$P$6:$P$605,Painel!$C$4) -> 350 | D31: =IF(N(IFERROR(INDEX(Categorias!$E$6:$E$45,MATCH(B31,Categorias!$B$6:$B$45,0)),0))>0,C31/IFERROR(INDEX(Categorias!$E$6:$E$45,MATCH(B31,Categorias!$B$6:$B$45,0)),0),"") -> 0.875 | E31: =IF(D31="","Sem limite",IF(D31>=1,"Crítico",IF(D31>=0.9,"Atenção","OK"))) -> OK
B32: =Categorias!B18 -> Lazer | C32: =SUMIFS(Lançamentos!$E$6:$E$605,Lançamentos!$D$6:$D$605,B32,Lançamentos!$P$6:$P$605,Painel!$C$4) -> 160 | D32: =IF(N(IFERROR(INDEX(Categorias!$E$6:$E$45,MATCH(B32,Categorias!$B$6:$B$45,0)),0))>0,C32/IFERROR(INDEX(Categorias!$E$6:$E$45,MATCH(B32,Categorias!$B$6:$B$45,0)),0),"") -> 0.64 | E32: =IF(D32="","Sem limite",IF(D32>=1,"Crítico",IF(D32>=0.9,"Atenção","OK"))) -> OK
B33: =Categorias!B19 -> Compras pessoais | C33: =SUMIFS(Lançamentos!$E$6:$E$605,Lançamentos!$D$6:$D$605,B33,Lançamentos!$P$6:$P$605,Painel!$C$4) -> 380 | D33: =IF(N(IFERROR(INDEX(Categorias!$E$6:$E$45,MATCH(B33,Categorias!$B$6:$B$45,0)),0))>0,C33/IFERROR(INDEX(Categorias!$E$6:$E$45,MATCH(B33,Categorias!$B$6:$B$45,0)),0),"") -> 1.2666667 | E33: =IF(D33="","Sem limite",IF(D33>=1,"Crítico",IF(D33>=0.9,"Atenção","OK"))) -> Crítico
B34: =Categorias!B20 -> Farmácia | C34: =SUMIFS(Lançamentos!$E$6:$E$605,Lançamentos!$D$6:$D$605,B34,Lançamentos!$P$6:$P$605,Painel!$C$4) -> 150 | D34: =IF(N(IFERROR(INDEX(Categorias!$E$6:$E$45,MATCH(B34,Categorias!$B$6:$B$45,0)),0))>0,C34/IFERROR(INDEX(Categorias!$E$6:$E$45,MATCH(B34,Categorias!$B$6:$B$45,0)),0),"") | E34: =IF(D34="","Sem limite",IF(D34>=1,"Crítico",IF(D34>=0.9,"Atenção","OK"))) -> Sem limite
... B39: =Categorias!B25 -> Cartão: fatura anterior | C39: =SUMIFS(Lançamentos!$E$6:$E$605,Lançamentos!$D$6:$D$605,B39,Lançamentos!$P$6:$P$605,Painel!$C$4) -> 0 | D39: =IF(N(IFERROR(INDEX(Categorias!$E$6:$E$45,MATCH(B39,Categorias!$B$6:$B$45,0)),0))>0,C39/IFERROR(INDEX(Categorias!$E$6:$E$45,MATCH(B39,Categorias!$B$6:$B$45,0)),0),"") | E39: =IF(D39="","Sem limite",IF(D39>=1,"Crítico",IF(D39>=0.9,"Atenção","OK"))) -> Sem limite

Sheet Categorias
B2: Categorias
B3: Pode renomear, apagar ou incluir linhas até a linha 45. O grupo define onde o valor entra nos cálculos. A área SMED vale para o Método ENOP·SMED. O limite do mês gera os alertas de 90% e 100%.
D4: S Saúde 5 · M Moradia e Finanças 4 · E Educação 3 · D Diversos/Diversão 2
B5: Categoria | C5: Grupo | D5: Área SMED | E5: Limite do mês (R$)
B6: Salário | C6: Entrada
B7: Renda extra | C7: Entrada
B8: Outras entradas | C8: Entrada
B9: Moradia | C9: Fixo | D9: M
B10: Contas da casa | C10: Fixo | D10: M
B11: Internet e celular | C11: Fixo | D11: M
B12: Educação | C12: Fixo | D12: E
B13: Saúde (plano) | C13: Fixo | D13: S
B14: Assinaturas | C14: Fixo | D14: D
B15: Mercado | C15: Variável | D15: M | E15: 1300
B16: Delivery e restaurantes | C16: Variável | D16: D | E16: 400
B17: Transporte | C17: Variável | D17: M | E17: 400
B18: Lazer | C18: Variável | D18: D | E18: 250
B19: Compras pessoais | C19: Variável | D19: D | E19: 300
B20: Farmácia | C20: Variável | D20: S
B21: Presentes | C21: Variável | D21: D | E21: 150
B22: Filhos | C22: Variável | D22: E
B23: Outros gastos | C23: Variável | D23: D
B24: Parcela de dívida | C24: Dívida | D24: M
B25: Cartão: fatura anterior | C25: Dívida | D25: M
B26: Reserva de emergência | C26: Guardado
B27: Investimentos | C27: Guardado
B28: Meta: viagem | C28: Guardado

Sheet Lançamentos
B2: Lançamentos
B3: Um lançamento por linha. Valores sempre positivos: o grupo da categoria diz se é entrada ou saída.
H4: ENOP·SMED: responda S ou N nas três perguntas (só para gastos). A área vem da categoria.
B5: Data | C5: Descrição | D5: Categoria | E5: Valor (R$) | F5: Pagamento | G5: Emoção | H5: Área SMED | I5: E/N agora? | J5: Cabe no orçam.? | K5: Não é postergável? | L5: Pontuação | M5: Decisão ENOP·SMED | O5: Grupo | P5: Mês
B6: 46331 | C6: Salário | D6: Salário | E6: 7900 | F6: Pix | H6: =IF(D6="","",IFERROR(INDEX(Categorias!$D$6:$D$45,MATCH(D6,Categorias!$B$6:$B$45,0))&"","")) | L6: =IF(OR(H6="",COUNTIF(I6:K6,"S")+COUNTIF(I6:K6,"N")<3),"",COUNTIF(I6:K6,"S")*IF(H6="S",5,IF(H6="M",4,IF(H6="E",3,2)))) | M6: =IF(L6="","",IF(L6>=12,"Executar",IF(L6>=8,"Executar com controle",IF(L6>=5,"Postergar","Cancelar")))) | O6: =IF(D6="","",IFERROR(INDEX(Categorias!$C$6:$C$45,MATCH(D6,Categorias!$B$6:$B$45,0)),"Sem grupo")) -> Entrada | P6: =IF(B6="","",DATE(YEAR(B6),MONTH(B6),1)) -> 46327
B7: 46338 | C7: Freela de consultoria | D7: Renda extra | E7: 800 | F7: Pix | H7: =IF(D7="","",IFERROR(INDEX(Categorias!$D$6:$D$45,MATCH(D7,Categorias!$B$6:$B$45,0))&"","")) | L7: =IF(OR(H7="",COUNTIF(I7:K7,"S")+COUNTIF(I7:K7,"N")<3),"",COUNTIF(I7:K7,"S")*IF(H7="S",5,IF(H7="M",4,IF(H7="E",3,2)))) | M7: =IF(L7="","",IF(L7>=12,"Executar",IF(L7>=8,"Executar com controle",IF(L7>=5,"Postergar","Cancelar")))) | O7: =IF(D7="","",IFERROR(INDEX(Categorias!$C$6:$C$45,MATCH(D7,Categorias!$B$6:$B$45,0)),"Sem grupo")) -> Entrada | P7: =IF(B7="","",DATE(YEAR(B7),MONTH(B7),1)) -> 46327
B8: 46331 | C8: Aluguel | D8: Moradia | E8: 1800 | F8: Pix | G8: Necessidade | H8: =IF(D8="","",IFERROR(INDEX(Categorias!$D$6:$D$45,MATCH(D8,Categorias!$B$6:$B$45,0))&"","")) -> M | I8: S | J8: S | K8: S | L8: =IF(OR(H8="",COUNTIF(I8:K8,"S")+COUNTIF(I8:K8,"N")<3),"",COUNTIF(I8:K8,"S")*IF(H8="S",5,IF(H8="M",4,IF(H8="E",3,2)))) -> 12 | M8: =IF(L8="","",IF(L8>=12,"Executar",IF(L8>=8,"Executar com controle",IF(L8>=5,"Postergar","Cancelar")))) -> Executar | O8: =IF(D8="","",IFERROR(INDEX(Categorias!$C$6:$C$45,MATCH(D8,Categorias!$B$6:$B$45,0)),"Sem grupo")) -> Fixo | P8: =IF(B8="","",DATE(YEAR(B8),MONTH(B8),1)) -> 46327
B9: 46336 | C9: Condomínio + IPTU | D9: Moradia | E9: 450 | F9: Boleto | G9: Necessidade | H9: =IF(D9="","",IFERROR(INDEX(Categorias!$D$6:$D$45,MATCH(D9,Categorias!$B$6:$B$45,0))&"","")) -> M | I9: S | J9: S | K9: S | L9: =IF(OR(H9="",COUNTIF(I9:K9,"S")+COUNTIF(I9:K9,"N")<3),"",COUNTIF(I9:K9,"S")*IF(H9="S",5,IF(H9="M",4,IF(H9="E",3,2)))) -> 12 | M9: =IF(L9="","",IF(L9>=12,"Executar",IF(L9>=8,"Executar com controle",IF(L9>=5,"Postergar","Cancelar")))) -> Executar | O9: =IF(D9="","",IFERROR(INDEX(Categorias!$C$6:$C$45,MATCH(D9,Categorias!$B$6:$B$45,0)),"Sem grupo")) -> Fixo | P9: =IF(B9="","",DATE(YEAR(B9),MONTH(B9),1)) -> 46327
B10: 46336 | C10: Luz, água e gás | D10: Contas da casa | E10: 320 | F10: Débito automático | G10: Necessidade | H10: =IF(D10="","",IFERROR(INDEX(Categorias!$D$6:$D$45,MATCH(D10,Categorias!$B$6:$B$45,0))&"","")) -> M | I10: S | J10: S | K10: S | L10: =IF(OR(H10="",COUNTIF(I10:K10,"S")+COUNTIF(I10:K10,"N")<3),"",COUNTIF(I10:K10,"S")*IF(H10="S",5,IF(H10="M",4,IF(H10="E",3,2)))) -> 12 | M10: =IF(L10="","",IF(L10>=12,"Executar",IF(L10>=8,"Executar com controle",IF(L10>=5,"Postergar","Cancelar")))) -> Executar | O10: =IF(D10="","",IFERROR(INDEX(Categorias!$C$6:$C$45,MATCH(D10,Categorias!$B$6:$B$45,0)),"Sem grupo")) -> Fixo | P10: =IF(B10="","",DATE(YEAR(B10),MONTH(B10),1)) -> 46327
B11: 46334 | C11: Internet e celular | D11: Internet e celular | E11: 180 | F11: Crédito | G11: Necessidade | H11: =IF(D11="","",IFERROR(INDEX(Categorias!$D$6:$D$45,MATCH(D11,Categorias!$B$6:$B$45,0))&"","")) -> M | I11: S | J11: S | K11: S | L11: =IF(OR(H11="",COUNTIF(I11:K11,"S")+COUNTIF(I11:K11,"N")<3),"",COUNTIF(I11:K11,"S")*IF(H11="S",5,IF(H11="M",4,IF(H11="E",3,2)))) -> 12 | M11: =IF(L11="","",IF(L11>=12,"Executar",IF(L11>=8,"Executar com controle",IF(L11>=5,"Postergar","Cancelar")))) -> Executar | O11: =IF(D11="","",IFERROR(INDEX(Categorias!$C$6:$C$45,MATCH(D11,Categorias!$B$6:$B$45,0)),"Sem grupo")) -> Fixo | P11: =IF(B11="","",DATE(YEAR(B11),MONTH(B11),1)) -> 46327
B12: 46331 | C12: Escola | D12: Educação | E12: 900 | F12: Boleto | G12: Necessidade | H12: =IF(D12="","",IFERROR(INDEX(Categorias!$D$6:$D$45,MATCH(D12,Categorias!$B$6:$B$45,0))&"","")) -> E | I12: S | J12: S | K12: S | L12: =IF(OR(H12="",COUNTIF(I12:K12,"S")+COUNTIF(I12:K12,"N")<3),"",COUNTIF(I12:K12,"S")*IF(H12="S",5,IF(H12="M",4,IF(H12="E",3,2)))) -> 9 | M12: =IF(L12="","",IF(L12>=12,"Executar",IF(L12>=8,"Executar com controle",IF(L12>=5,"Postergar","Cancelar")))) -> Executar com controle | O12: =IF(D12="","",IFERROR(INDEX(Categorias!$C$6:$C$45,MATCH(D12,Categorias!$B$6:$B$45,0)),"Sem grupo")) -> Fixo | P12: =IF(B12="","",DATE(YEAR(B12),MONTH(B12),1)) -> 46327
B13: 46333 | C13: Plano de saúde | D13: Saúde (plano) | E13: 650 | F13: Débito automático | G13: Necessidade | H13: =IF(D13="","",IFERROR(INDEX(Categorias!$D$6:$D$45,MATCH(D13,Categorias!$B$6:$B$45,0))&"","")) -> S | I13: S | J13: S | K13: S | L13: =IF(OR(H13="",COUNTIF(I13:K13,"S")+COUNTIF(I13:K13,"N")<3),"",COUNTIF(I13:K13,"S")*IF(H13="S",5,IF(H13="M",4,IF(H13="E",3,2)))) -> 15 | M13: =IF(L13="","",IF(L13>=12,"Executar",IF(L13>=8,"Executar com controle",IF(L13>=5,"Postergar","Cancelar")))) -> Executar | O13: =IF(D13="","",IFERROR(INDEX(Categorias!$C$6:$C$45,MATCH(D13,Categorias!$B$6:$B$45,0)),"Sem grupo")) -> Fixo | P13: =IF(B13="","",DATE(YEAR(B13),MONTH(B13),1)) -> 46327
B14: 46335 | C14: Streaming e academia | D14: Assinaturas | E14: 160 | F14: Crédito | G14: Alegria | H14: =IF(D14="","",IFERROR(INDEX(Categorias!$D$6:$D$45,MATCH(D14,Categorias!$B$6:$B$45,0))&"","")) -> D | I14: N | J14: S | K14: N | L14: =IF(OR(H14="",COUNTIF(I14:K14,"S")+COUNTIF(I14:K14,"N")<3),"",COUNTIF(I14:K14,"S")*IF(H14="S",5,IF(H14="M",4,IF(H14="E",3,2)))) -> 2 | M14: =IF(L14="","",IF(L14>=12,"Executar",IF(L14>=8,"Executar com controle",IF(L14>=5,"Postergar","Cancelar")))) -> Cancelar | O14: =IF(D14="","",IFERROR(INDEX(Categorias!$C$6:$C$45,MATCH(D14,Categorias!$B$6:$B$45,0)),"Sem grupo")) -> Fixo | P14: =IF(B14="","",DATE(YEAR(B14),MONTH(B14),1)) -> 46327
B15: 46332 | C15: Mercado do mês | D15: Mercado | E15: 780 | F15: Crédito | G15: Necessidade | H15: =IF(D15="","",IFERROR(INDEX(Categorias!$D$6:$D$45,MATCH(D15,Categorias!$B$6:$B$45,0))&"","")) -> M | I15: S | J15: S | K15: S | L15: =IF(OR(H15="",COUNTIF(I15:K15,"S")+COUNTIF(I15:K15,"N")<3),"",COUNTIF(I15:K15,"S")*IF(H15="S",5,IF(H15="M",4,IF(H15="E",3,2)))) -> 12 | M15: =IF(L15="","",IF(L15>=12,"Executar",IF(L15>=8,"Executar com controle",IF(L15>=5,"Postergar","Cancelar")))) -> Executar | O15: =IF(D15="","",IFERROR(INDEX(Categorias!$C$6:$C$45,MATCH(D15,Categorias!$B$6:$B$45,0)),"Sem grupo")) -> Variável | P15: =IF(B15="","",DATE(YEAR(B15),MONTH(B15),1)) -> 46327
B16: 46346 | C16: Feira e reposição | D16: Mercado | E16: 420 | F16: Débito | G16: Necessidade | H16: =IF(D16="","",IFERROR(INDEX(Categorias!$D$6:$D$45,MATCH(D16,Categorias!$B$6:$B$45,0))&"","")) -> M | I16: S | J16: S | K16: S | L16: =IF(OR(H16="",COUNTIF(I16:K16,"S")+COUNTIF(I16:K16,"N")<3),"",COUNTIF(I16:K16,"S")*IF(H16="S",5,IF(H16="M",4,IF(H16="E",3,2)))) -> 12 | M16: =IF(L16="","",IF(L16>=12,"Executar",IF(L16>=8,"Executar com controle",IF(L16>=5,"Postergar","Cancelar")))) -> Executar | O16: =IF(D16="","",IFERROR(INDEX(Categorias!$C$6:$C$45,MATCH(D16,Categorias!$B$6:$B$45,0)),"Sem grupo")) -> Variável | P16: =IF(B16="","",DATE(YEAR(B16),MONTH(B16),1)) -> 46327
B17: 46333 | C17: Pizza de sexta | D17: Delivery e restaurantes | E17: 110 | F17: Crédito | G17: Alegria | H17: =IF(D17="","",IFERROR(INDEX(Categorias!$D$6:$D$45,MATCH(D17,Categorias!$B$6:$B$45,0))&"","")) -> D | I17: N | J17: S | K17: N | L17: =IF(OR(H17="",COUNTIF(I17:K17,"S")+COUNTIF(I17:K17,"N")<3),"",COUNTIF(I17:K17,"S")*IF(H17="S",5,IF(H17="M",4,IF(H17="E",3,2)))) -> 2 | M17: =IF(L17="","",IF(L17>=12,"Executar",IF(L17>=8,"Executar com controle",IF(L17>=5,"Postergar","Cancelar")))) -> Cancelar | O17: =IF(D17="","",IFERROR(INDEX(Categorias!$C$6:$C$45,MATCH(D17,Categorias!$B$6:$B$45,0)),"Sem grupo")) -> Variável | P17: =IF(B17="","",DATE(YEAR(B17),MONTH(B17),1)) -> 46327
B18: 46339 | C18: Delivery depois do trabalho | D18: Delivery e restaurantes | E18: 95 | F18: Crédito | G18: Estresse | H18: =IF(D18="","",IFERROR(INDEX(Categorias!$D$6:$D$45,MATCH(D18,Categorias!$B$6:$B$45,0))&"","")) -> D | I18: N | J18: S | K18: N | L18: =IF(OR(H18="",COUNTIF(I18:K18,"S")+COUNTIF(I18:K18,"N")<3),"",COUNTIF(I18:K18,"S")*IF(H18="S",5,IF(H18="M",4,IF(H18="E",3,2)))) -> 2 | M18: =IF(L18="","",IF(L18>=12,"Executar",IF(L18>=8,"Executar com controle",IF(L18>=5,"Postergar","Cancelar")))) -> Cancelar | O18: =IF(D18="","",IFERROR(INDEX(Categorias!$C$6:$C$45,MATCH(D18,Categorias!$B$6:$B$45,0)),"Sem grupo")) -> Variável | P18: =IF(B18="","",DATE(YEAR(B18),MONTH(B18),1)) -> 46327
B19: 46344 | C19: Almoço com amigas | D19: Delivery e restaurantes | E19: 140 | F19: Pix | G19: Pressão social | H19: =IF(D19="","",IFERROR(INDEX(Categorias!$D$6:$D$45,MATCH(D19,Categorias!$B$6:$B$45,0))&"","")) -> D | I19: N | J19: S | K19: N | L19: =IF(OR(H19="",COUNTIF(I19:K19,"S")+COUNTIF(I19:K19,"N")<3),"",COUNTIF(I19:K19,"S")*IF(H19="S",5,IF(H19="M",4,IF(H19="E",3,2)))) -> 2 | M19: =IF(L19="","",IF(L19>=12,"Executar",IF(L19>=8,"Executar com controle",IF(L19>=5,"Postergar","Cancelar")))) -> Cancelar | O19: =IF(D19="","",IFERROR(INDEX(Categorias!$C$6:$C$45,MATCH(D19,Categorias!$B$6:$B$45,0)),"Sem grupo")) -> Variável | P19: =IF(B19="","",DATE(YEAR(B19),MONTH(B19),1)) -> 46327
... B29: 46336 | C29: Parcela loja | D29: Parcela de dívida | E29: 400 | F29: Crédito | G29: Necessidade | H29: =IF(D29="","",IFERROR(INDEX(Categorias!$D$6:$D$45,MATCH(D29,Categorias!$B$6:$B$45,0))&"","")) -> M | I29: S | J29: S | K29: S | L29: =IF(OR(H29="",COUNTIF(I29:K29,"S")+COUNTIF(I29:K29,"N")<3),"",COUNTIF(I29:K29,"S")*IF(H29="S",5,IF(H29="M",4,IF(H29="E",3,2)))) -> 12 | M29: =IF(L29="","",IF(L29>=12,"Executar",IF(L29>=8,"Executar com controle",IF(L29>=5,"Postergar","Cancelar")))) -> Executar | O29: =IF(D29="","",IFERROR(INDEX(Categorias!$C$6:$C$45,MATCH(D29,Categorias!$B$6:$B$45,0)),"Sem grupo")) -> Dívida | P29: =IF(B29="","",DATE(YEAR(B29),MONTH(B29),1)) -> 46327
B30: 46332 | C30: Transferência automática | D30: Reserva de emergência | E30: 300 | F30: Pix | H30: =IF(D30="","",IFERROR(INDEX(Categorias!$D$6:$D$45,MATCH(D30,Categorias!$B$6:$B$45,0))&"","")) | L30: =IF(OR(H30="",COUNTIF(I30:K30,"S")+COUNTIF(I30:K30,"N")<3),"",COUNTIF(I30:K30,"S")*IF(H30="S",5,IF(H30="M",4,IF(H30="E",3,2)))) | M30: =IF(L30="","",IF(L30>=12,"Executar",IF(L30>=8,"Executar com controle",IF(L30>=5,"Postergar","Cancelar")))) | O30: =IF(D30="","",IFERROR(INDEX(Categorias!$C$6:$C$45,MATCH(D30,Categorias!$B$6:$B$45,0)),"Sem grupo")) -> Guardado | P30: =IF(B30="","",DATE(YEAR(B30),MONTH(B30),1)) -> 46327
B31: 46332 | C31: Guardar para a viagem | D31: Meta: viagem | E31: 150 | F31: Pix | H31: =IF(D31="","",IFERROR(INDEX(Categorias!$D$6:$D$45,MATCH(D31,Categorias!$B$6:$B$45,0))&"","")) | L31: =IF(OR(H31="",COUNTIF(I31:K31,"S")+COUNTIF(I31:K31,"N")<3),"",COUNTIF(I31:K31,"S")*IF(H31="S",5,IF(H31="M",4,IF(H31="E",3,2)))) | M31: =IF(L31="","",IF(L31>=12,"Executar",IF(L31>=8,"Executar com controle",IF(L31>=5,"Postergar","Cancelar")))) | O31: =IF(D31="","",IFERROR(INDEX(Categorias!$C$6:$C$45,MATCH(D31,Categorias!$B$6:$B$45,0)),"Sem grupo")) -> Guardado | P31: =IF(B31="","",DATE(YEAR(B31),MONTH(B31),1)) -> 46327
H32: =IF(D32="","",IFERROR(INDEX(Categorias!$D$6:$D$45,MATCH(D32,Categorias!$B$6:$B$45,0))&"","")) | L32: =IF(OR(H32="",COUNTIF(I32:K32,"S")+COUNTIF(I32:K32,"N")<3),"",COUNTIF(I32:K32,"S")*IF(H32="S",5,IF(H32="M",4,IF(H32="E",3,2)))) | M32: =IF(L32="","",IF(L32>=12,"Executar",IF(L32>=8,"Executar com controle",IF(L32>=5,"Postergar","Cancelar")))) | O32: =IF(D32="","",IFERROR(INDEX(Categorias!$C$6:$C$45,MATCH(D32,Categorias!$B$6:$B$45,0)),"Sem grupo")) | P32: =IF(B32="","",DATE(YEAR(B32),MONTH(B32),1))
H33: =IF(D33="","",IFERROR(INDEX(Categorias!$D$6:$D$45,MATCH(D33,Categorias!$B$6:$B$45,0))&"","")) | L33: =IF(OR(H33="",COUNTIF(I33:K33,"S")+COUNTIF(I33:K33,"N")<3),"",COUNTIF(I33:K33,"S")*IF(H33="S",5,IF(H33="M",4,IF(H33="E",3,2)))) | M33: =IF(L33="","",IF(L33>=12,"Executar",IF(L33>=8,"Executar com controle",IF(L33>=5,"Postergar","Cancelar")))) | O33: =IF(D33="","",IFERROR(INDEX(Categorias!$C$6:$C$45,MATCH(D33,Categorias!$B$6:$B$45,0)),"Sem grupo")) | P33: =IF(B33="","",DATE(YEAR(B33),MONTH(B33),1))
H34: =IF(D34="","",IFERROR(INDEX(Categorias!$D$6:$D$45,MATCH(D34,Categorias!$B$6:$B$45,0))&"","")) | L34: =IF(OR(H34="",COUNTIF(I34:K34,"S")+COUNTIF(I34:K34,"N")<3),"",COUNTIF(I34:K34,"S")*IF(H34="S",5,IF(H34="M",4,IF(H34="E",3,2)))) | M34: =IF(L34="","",IF(L34>=12,"Executar",IF(L34>=8,"Executar com controle",IF(L34>=5,"Postergar","Cancelar")))) | O34: =IF(D34="","",IFERROR(INDEX(Categorias!$C$6:$C$45,MATCH(D34,Categorias!$B$6:$B$45,0)),"Sem grupo")) | P34: =IF(B34="","",DATE(YEAR(B34),MONTH(B34),1))
H35: =IF(D35="","",IFERROR(INDEX(Categorias!$D$6:$D$45,MATCH(D35,Categorias!$B$6:$B$45,0))&"","")) | L35: =IF(OR(H35="",COUNTIF(I35:K35,"S")+COUNTIF(I35:K35,"N")<3),"",COUNTIF(I35:K35,"S")*IF(H35="S",5,IF(H35="M",4,IF(H35="E",3,2)))) | M35: =IF(L35="","",IF(L35>=12,"Executar",IF(L35>=8,"Executar com controle",IF(L35>=5,"Postergar","Cancelar")))) | O35: =IF(D35="","",IFERROR(INDEX(Categorias!$C$6:$C$45,MATCH(D35,Categorias!$B$6:$B$45,0)),"Sem grupo")) | P35: =IF(B35="","",DATE(YEAR(B35),MONTH(B35),1))
H36: =IF(D36="","",IFERROR(INDEX(Categorias!$D$6:$D$45,MATCH(D36,Categorias!$B$6:$B$45,0))&"","")) | L36: =IF(OR(H36="",COUNTIF(I36:K36,"S")+COUNTIF(I36:K36,"N")<3),"",COUNTIF(I36:K36,"S")*IF(H36="S",5,IF(H36="M",4,IF(H36="E",3,2)))) | M36: =IF(L36="","",IF(L36>=12,"Executar",IF(L36>=8,"Executar com controle",IF(L36>=5,"Postergar","Cancelar")))) | O36: =IF(D36="","",IFERROR(INDEX(Categorias!$C$6:$C$45,MATCH(D36,Categorias!$B$6:$B$45,0)),"Sem grupo")) | P36: =IF(B36="","",DATE(YEAR(B36),MONTH(B36),1))
H37: =IF(D37="","",IFERROR(INDEX(Categorias!$D$6:$D$45,MATCH(D37,Categorias!$B$6:$B$45,0))&"","")) | L37: =IF(OR(H37="",COUNTIF(I37:K37,"S")+COUNTIF(I37:K37,"N")<3),"",COUNTIF(I37:K37,"S")*IF(H37="S",5,IF(H37="M",4,IF(H37="E",3,2)))) | M37: =IF(L37="","",IF(L37>=12,"Executar",IF(L37>=8,"Executar com controle",IF(L37>=5,"Postergar","Cancelar")))) | O37: =IF(D37="","",IFERROR(INDEX(Categorias!$C$6:$C$45,MATCH(D37,Categorias!$B$6:$B$45,0)),"Sem grupo")) | P37: =IF(B37="","",DATE(YEAR(B37),MONTH(B37),1))
H38: =IF(D38="","",IFERROR(INDEX(Categorias!$D$6:$D$45,MATCH(D38,Categorias!$B$6:$B$45,0))&"","")) | L38: =IF(OR(H38="",COUNTIF(I38:K38,"S")+COUNTIF(I38:K38,"N")<3),"",COUNTIF(I38:K38,"S")*IF(H38="S",5,IF(H38="M",4,IF(H38="E",3,2)))) | M38: =IF(L38="","",IF(L38>=12,"Executar",IF(L38>=8,"Executar com controle",IF(L38>=5,"Postergar","Cancelar")))) | O38: =IF(D38="","",IFERROR(INDEX(Categorias!$C$6:$C$45,MATCH(D38,Categorias!$B$6:$B$45,0)),"Sem grupo")) | P38: =IF(B38="","",DATE(YEAR(B38),MONTH(B38),1))
H39: =IF(D39="","",IFERROR(INDEX(Categorias!$D$6:$D$45,MATCH(D39,Categorias!$B$6:$B$45,0))&"","")) | L39: =IF(OR(H39="",COUNTIF(I39:K39,"S")+COUNTIF(I39:K39,"N")<3),"",COUNTIF(I39:K39,"S")*IF(H39="S",5,IF(H39="M",4,IF(H39="E",3,2)))) | M39: =IF(L39="","",IF(L39>=12,"Executar",IF(L39>=8,"Executar com controle",IF(L39>=5,"Postergar","Cancelar")))) | O39: =IF(D39="","",IFERROR(INDEX(Categorias!$C$6:$C$45,MATCH(D39,Categorias!$B$6:$B$45,0)),"Sem grupo")) | P39: =IF(B39="","",DATE(YEAR(B39),MONTH(B39),1))
H40: =IF(D40="","",IFERROR(INDEX(Categorias!$D$6:$D$45,MATCH(D40,Categorias!$B$6:$B$45,0))&"","")) | L40: =IF(OR(H40="",COUNTIF(I40:K40,"S")+COUNTIF(I40:K40,"N")<3),"",COUNTIF(I40:K40,"S")*IF(H40="S",5,IF(H40="M",4,IF(H40="E",3,2)))) | M40: =IF(L40="","",IF(L40>=12,"Executar",IF(L40>=8,"Executar com controle",IF(L40>=5,"Postergar","Cancelar")))) | O40: =IF(D40="","",IFERROR(INDEX(Categorias!$C$6:$C$45,MATCH(D40,Categorias!$B$6:$B$45,0)),"Sem grupo")) | P40: =IF(B40="","",DATE(YEAR(B40),MONTH(B40),1))
H41: =IF(D41="","",IFERROR(INDEX(Categorias!$D$6:$D$45,MATCH(D41,Categorias!$B$6:$B$45,0))&"","")) | L41: =IF(OR(H41="",COUNTIF(I41:K41,"S")+COUNTIF(I41:K41,"N")<3),"",COUNTIF(I41:K41,"S")*IF(H41="S",5,IF(H41="M",4,IF(H41="E",3,2)))) | M41: =IF(L41="","",IF(L41>=12,"Executar",IF(L41>=8,"Executar com controle",IF(L41>=5,"Postergar","Cancelar")))) | O41: =IF(D41="","",IFERROR(INDEX(Categorias!$C$6:$C$45,MATCH(D41,Categorias!$B$6:$B$45,0)),"Sem grupo")) | P41: =IF(B41="","",DATE(YEAR(B41),MONTH(B41),1))
H42: =IF(D42="","",IFERROR(INDEX(Categorias!$D$6:$D$45,MATCH(D42,Categorias!$B$6:$B$45,0))&"","")) | L42: =IF(OR(H42="",COUNTIF(I42:K42,"S")+COUNTIF(I42:K42,"N")<3),"",COUNTIF(I42:K42,"S")*IF(H42="S",5,IF(H42="M",4,IF(H42="E",3,2)))) | M42: =IF(L42="","",IF(L42>=12,"Executar",IF(L42>=8,"Executar com controle",IF(L42>=5,"Postergar","Cancelar")))) | O42: =IF(D42="","",IFERROR(INDEX(Categorias!$C$6:$C$45,MATCH(D42,Categorias!$B$6:$B$45,0)),"Sem grupo")) | P42: =IF(B42="","",DATE(YEAR(B42),MONTH(B42),1))
H43: =IF(D43="","",IFERROR(INDEX(Categorias!$D$6:$D$45,MATCH(D43,Categorias!$B$6:$B$45,0))&"","")) | L43: =IF(OR(H43="",COUNTIF(I43:K43,"S")+COUNTIF(I43:K43,"N")<3),"",COUNTIF(I43:K43,"S")*IF(H43="S",5,IF(H43="M",4,IF(H43="E",3,2)))) | M43: =IF(L43="","",IF(L43>=12,"Executar",IF(L43>=8,"Executar com controle",IF(L43>=5,"Postergar","Cancelar")))) | O43: =IF(D43="","",IFERROR(INDEX(Categorias!$C$6:$C$45,MATCH(D43,Categorias!$B$6:$B$45,0)),"Sem grupo")) | P43: =IF(B43="","",DATE(YEAR(B43),MONTH(B43),1))
... H605: =IF(D605="","",IFERROR(INDEX(Categorias!$D$6:$D$45,MATCH(D605,Categorias!$B$6:$B$45,0))&"","")) | L605: =IF(OR(H605="",COUNTIF(I605:K605,"S")+COUNTIF(I605:K605,"N")<3),"",COUNTIF(I605:K605,"S")*IF(H605="S",5,IF(H605="M",4,IF(H605="E",3,2)))) | M605: =IF(L605="","",IF(L605>=12,"Executar",IF(L605>=8,"Executar com controle",IF(L605>=5,"Postergar","Cancelar")))) | O605: =IF(D605="","",IFERROR(INDEX(Categorias!$C$6:$C$45,MATCH(D605,Categorias!$B$6:$B$45,0)),"Sem grupo")) | P605: =IF(B605="","",DATE(YEAR(B605),MONTH(B605),1))

Sheet Metas
B2: Metas
B3: A primeira linha é a reserva de emergência: o Painel usa o valor guardado dela para calcular os meses de reserva.
B5: Objetivo | C5: Valor alvo (R$) | D5: Prazo | E5: Já guardado (R$) | F5: % atingido | G5: Falta (R$) | H5: Meses até o prazo | I5: Guardar por mês (R$)
B6: Reserva de emergência | C6: 27000 | D6: 46722 | E6: 4000 | F6: =IF(N(C6)=0,"",MIN(1,N(E6)/C6)) -> 0.14814815 | G6: =IF(N(C6)=0,"",MAX(0,C6-N(E6))) -> 23000 | H6: =IF(OR(N(C6)=0,D6=""),"",MAX(1,(YEAR(D6)-YEAR(Painel!$C$4))*12+MONTH(D6)-MONTH(Painel!$C$4))) -> 13 | I6: =IF(H6="","",G6/H6) -> 1769.2308
B7: Viagem em família | C7: 6000 | D7: 46569 | E7: 800 | F7: =IF(N(C7)=0,"",MIN(1,N(E7)/C7)) -> 0.13333333 | G7: =IF(N(C7)=0,"",MAX(0,C7-N(E7))) -> 5200 | H7: =IF(OR(N(C7)=0,D7=""),"",MAX(1,(YEAR(D7)-YEAR(Painel!$C$4))*12+MONTH(D7)-MONTH(Painel!$C$4))) -> 8 | I7: =IF(H7="","",G7/H7) -> 650
B8: Trocar o notebook | C8: 4500 | D8: 46661 | E8: 0 | F8: =IF(N(C8)=0,"",MIN(1,N(E8)/C8)) -> 0 | G8: =IF(N(C8)=0,"",MAX(0,C8-N(E8))) -> 4500 | H8: =IF(OR(N(C8)=0,D8=""),"",MAX(1,(YEAR(D8)-YEAR(Painel!$C$4))*12+MONTH(D8)-MONTH(Painel!$C$4))) -> 11 | I8: =IF(H8="","",G8/H8) -> 409.09091
F9: =IF(N(C9)=0,"",MIN(1,N(E9)/C9)) | G9: =IF(N(C9)=0,"",MAX(0,C9-N(E9))) | H9: =IF(OR(N(C9)=0,D9=""),"",MAX(1,(YEAR(D9)-YEAR(Painel!$C$4))*12+MONTH(D9)-MONTH(Painel!$C$4))) | I9: =IF(H9="","",G9/H9)
F10: =IF(N(C10)=0,"",MIN(1,N(E10)/C10)) | G10: =IF(N(C10)=0,"",MAX(0,C10-N(E10))) | H10: =IF(OR(N(C10)=0,D10=""),"",MAX(1,(YEAR(D10)-YEAR(Painel!$C$4))*12+MONTH(D10)-MONTH(Painel!$C$4))) | I10: =IF(H10="","",G10/H10)
F11: =IF(N(C11)=0,"",MIN(1,N(E11)/C11)) | G11: =IF(N(C11)=0,"",MAX(0,C11-N(E11))) | H11: =IF(OR(N(C11)=0,D11=""),"",MAX(1,(YEAR(D11)-YEAR(Painel!$C$4))*12+MONTH(D11)-MONTH(Painel!$C$4))) | I11: =IF(H11="","",G11/H11)
F12: =IF(N(C12)=0,"",MIN(1,N(E12)/C12)) | G12: =IF(N(C12)=0,"",MAX(0,C12-N(E12))) | H12: =IF(OR(N(C12)=0,D12=""),"",MAX(1,(YEAR(D12)-YEAR(Painel!$C$4))*12+MONTH(D12)-MONTH(Painel!$C$4))) | I12: =IF(H12="","",G12/H12)
F13: =IF(N(C13)=0,"",MIN(1,N(E13)/C13)) | G13: =IF(N(C13)=0,"",MAX(0,C13-N(E13))) | H13: =IF(OR(N(C13)=0,D13=""),"",MAX(1,(YEAR(D13)-YEAR(Painel!$C$4))*12+MONTH(D13)-MONTH(Painel!$C$4))) | I13: =IF(H13="","",G13/H13)
F14: =IF(N(C14)=0,"",MIN(1,N(E14)/C14)) | G14: =IF(N(C14)=0,"",MAX(0,C14-N(E14))) | H14: =IF(OR(N(C14)=0,D14=""),"",MAX(1,(YEAR(D14)-YEAR(Painel!$C$4))*12+MONTH(D14)-MONTH(Painel!$C$4))) | I14: =IF(H14="","",G14/H14)
F15: =IF(N(C15)=0,"",MIN(1,N(E15)/C15)) | G15: =IF(N(C15)=0,"",MAX(0,C15-N(E15))) | H15: =IF(OR(N(C15)=0,D15=""),"",MAX(1,(YEAR(D15)-YEAR(Painel!$C$4))*12+MONTH(D15)-MONTH(Painel!$C$4))) | I15: =IF(H15="","",G15/H15)
