Workbook

Sheet Como usar
B2: Seus 4 indicadores, mês a mês
B3: Finanças que Curam · Grupo FQC · Comunidade Manada · Por Aline Seabra
B5: Na minha área, ninguém decide sem indicador. Na vida pessoal deveria ser igual.
B7: Como preencher
B8: 1. Uma vez por mês, no mesmo dia, preencha uma linha da aba Meses: entradas, gastos fixos, gastos variáveis, parcelas de dívidas e quanto você tem de reserva.
B9: 2. A aba Meses calcula os 4 indicadores e o semáforo de cada um.
B10: 3. A aba Painel mostra o último mês preenchido e os gráficos da evolução.
B11: 4. Não precisa acertar centavo. O que importa é a tendência.
B13: Legenda
B14: Célula amarela = você preenche. Texto azul = valor de exemplo. Texto preto = cálculo automático, não apague.
B16: Os 4 indicadores
B17: Taxa de poupança = quanto sobrou ÷ entradas. Meta inicial: 10% ou mais.
... B22: Conteúdo educativo. Não é recomendação de investimento.

Sheet Painel
B2: Painel
B3: Último mês preenchido: | C3: =IFERROR(INDEX(Meses!$B$6:$B$17,MATCH(9.99E+307,Meses!$C$6:$C$17)),"Nenhum") -> Jan/27
B5: Indicador | C5: Último mês | D5: Situação | E5: O que observar
B6: Taxa de poupança | C6: =IFERROR(INDEX(Meses!$I$6:$I$17,MATCH(9.99E+307,Meses!$C$6:$C$17)),"") -> 0.04137931 | D6: =IFERROR(INDEX(Meses!$J$6:$J$17,MATCH(9.99E+307,Meses!$C$6:$C$17)),"") -> Atenção | E6: Meta inicial: 10% ou mais da renda guardada todo mês.
B7: Índice de endividamento | C7: =IFERROR(INDEX(Meses!$K$6:$K$17,MATCH(9.99E+307,Meses!$C$6:$C$17)),"") -> 0.10574713 | D7: =IFERROR(INDEX(Meses!$L$6:$L$17,MATCH(9.99E+307,Meses!$C$6:$C$17)),"") -> Atenção | E7: Até 10% é saudável. Acima de 20%, renegociar vira prioridade. Rotativo ou cheque especial: trate como alerta.
B8: Meses de reserva | C8: =IFERROR(INDEX(Meses!$M$6:$M$17,MATCH(9.99E+307,Meses!$C$6:$C$17)),"") -> 1.0619469 | D8: =IFERROR(INDEX(Meses!$N$6:$N$17,MATCH(9.99E+307,Meses!$C$6:$C$17)),"") -> Alerta | E8: De 3 a 6 meses do custo fixo. Renda variável: de 6 a 12.
B9: Peso do custo fixo | C9: =IFERROR(INDEX(Meses!$O$6:$O$17,MATCH(9.99E+307,Meses!$C$6:$C$17)),"") -> 0.51954023 | D9: =IFERROR(INDEX(Meses!$P$6:$P$17,MATCH(9.99E+307,Meses!$C$6:$C$17)),"") -> Atenção | E9: Quanto menor, mais liberdade para escolher.
B11: Reserva acumulada | C11: =IFERROR(INDEX(Meses!$G$6:$G$17,MATCH(9.99E+307,Meses!$C$6:$C$17)),"") -> 4800
B12: Quanto sobrou somando todos os meses | C12: =SUM(Meses!H6:H17) -> 1090
B20: Referências dos semáforos (pode ajustar)
B21: Referências educativas da Manada.
B22: Taxa de poupança saudável a partir de | C22: 0.1
B23: Endividamento saudável até | C23: 0.1
B24: Endividamento em atenção até | C24: 0.2
B25: Reserva em atenção a partir de (meses) | C25: 3
B26: Reserva saudável a partir de (meses) | C26: 6
B27: Custo fixo saudável até | C27: 0.5
B28: Custo fixo em atenção até | C28: 0.65

Sheet Meses
B2: Registro mensal
B3: Preencha as colunas amarelas uma vez por mês. Deixe em branco os meses que ainda não chegaram.
B5: Mês | C5: Entradas (R$) | D5: Gastos fixos (R$) | E5: Gastos variáveis (R$) | F5: Parcelas de dívidas (R$) | G5: Reserva hoje (R$) | H5: Sobra (R$) | I5: Taxa de poupança | J5: Situação | K5: Endivida­mento | L5: Situação | M5: Meses de reserva | N5: Situação | O5: Peso do custo fixo | P5: Situação
B6: Nov/26 | C6: 8700 | D6: 4460 | E6: 3110 | F6: 920 | G6: 4000 | H6: =IF(N(C6)=0,"",C6-D6-E6-F6) -> 210 | I6: =IF(N(C6)=0,"",MAX(H6,0)/C6) -> 0.024137931 | J6: =IF(I6="","",IF(I6>=Painel!$C$22,"Saudável",IF(I6>0,"Atenção","Alerta"))) -> Atenção | K6: =IF(N(C6)=0,"",F6/C6) -> 0.10574713 | L6: =IF(K6="","",IF(K6<=Painel!$C$23,"Saudável",IF(K6<=Painel!$C$24,"Atenção","Alerta"))) -> Atenção | M6: =IF(OR(N(C6)=0,N(D6)=0),"",G6/D6) -> 0.89686099 | N6: =IF(M6="","",IF(M6>=Painel!$C$26,"Saudável",IF(M6>=Painel!$C$25,"Atenção","Alerta"))) -> Alerta | O6: =IF(N(C6)=0,"",D6/C6) -> 0.51264368 | P6: =IF(O6="","",IF(O6<=Painel!$C$27,"Saudável",IF(O6<=Painel!$C$28,"Atenção","Alerta"))) -> Atenção
B7: Dez/26 | C7: 9400 | D7: 4460 | E7: 3500 | F7: 920 | G7: 4300 | H7: =IF(N(C7)=0,"",C7-D7-E7-F7) -> 520 | I7: =IF(N(C7)=0,"",MAX(H7,0)/C7) -> 0.055319149 | J7: =IF(I7="","",IF(I7>=Painel!$C$22,"Saudável",IF(I7>0,"Atenção","Alerta"))) -> Atenção | K7: =IF(N(C7)=0,"",F7/C7) -> 0.09787234 | L7: =IF(K7="","",IF(K7<=Painel!$C$23,"Saudável",IF(K7<=Painel!$C$24,"Atenção","Alerta"))) -> Saudável | M7: =IF(OR(N(C7)=0,N(D7)=0),"",G7/D7) -> 0.96412556 | N7: =IF(M7="","",IF(M7>=Painel!$C$26,"Saudável",IF(M7>=Painel!$C$25,"Atenção","Alerta"))) -> Alerta | O7: =IF(N(C7)=0,"",D7/C7) -> 0.47446809 | P7: =IF(O7="","",IF(O7<=Painel!$C$27,"Saudável",IF(O7<=Painel!$C$28,"Atenção","Alerta"))) -> Saudável
B8: Jan/27 | C8: 8700 | D8: 4520 | E8: 2900 | F8: 920 | G8: 4800 | H8: =IF(N(C8)=0,"",C8-D8-E8-F8) -> 360 | I8: =IF(N(C8)=0,"",MAX(H8,0)/C8) -> 0.04137931 | J8: =IF(I8="","",IF(I8>=Painel!$C$22,"Saudável",IF(I8>0,"Atenção","Alerta"))) -> Atenção | K8: =IF(N(C8)=0,"",F8/C8) -> 0.10574713 | L8: =IF(K8="","",IF(K8<=Painel!$C$23,"Saudável",IF(K8<=Painel!$C$24,"Atenção","Alerta"))) -> Atenção | M8: =IF(OR(N(C8)=0,N(D8)=0),"",G8/D8) -> 1.0619469 | N8: =IF(M8="","",IF(M8>=Painel!$C$26,"Saudável",IF(M8>=Painel!$C$25,"Atenção","Alerta"))) -> Alerta | O8: =IF(N(C8)=0,"",D8/C8) -> 0.51954023 | P8: =IF(O8="","",IF(O8<=Painel!$C$27,"Saudável",IF(O8<=Painel!$C$28,"Atenção","Alerta"))) -> Atenção
B9: Fev/27 | H9: =IF(N(C9)=0,"",C9-D9-E9-F9) | I9: =IF(N(C9)=0,"",MAX(H9,0)/C9) | J9: =IF(I9="","",IF(I9>=Painel!$C$22,"Saudável",IF(I9>0,"Atenção","Alerta"))) | K9: =IF(N(C9)=0,"",F9/C9) | L9: =IF(K9="","",IF(K9<=Painel!$C$23,"Saudável",IF(K9<=Painel!$C$24,"Atenção","Alerta"))) | M9: =IF(OR(N(C9)=0,N(D9)=0),"",G9/D9) | N9: =IF(M9="","",IF(M9>=Painel!$C$26,"Saudável",IF(M9>=Painel!$C$25,"Atenção","Alerta"))) | O9: =IF(N(C9)=0,"",D9/C9) | P9: =IF(O9="","",IF(O9<=Painel!$C$27,"Saudável",IF(O9<=Painel!$C$28,"Atenção","Alerta")))
B10: Mar/27 | H10: =IF(N(C10)=0,"",C10-D10-E10-F10) | I10: =IF(N(C10)=0,"",MAX(H10,0)/C10) | J10: =IF(I10="","",IF(I10>=Painel!$C$22,"Saudável",IF(I10>0,"Atenção","Alerta"))) | K10: =IF(N(C10)=0,"",F10/C10) | L10: =IF(K10="","",IF(K10<=Painel!$C$23,"Saudável",IF(K10<=Painel!$C$24,"Atenção","Alerta"))) | M10: =IF(OR(N(C10)=0,N(D10)=0),"",G10/D10) | N10: =IF(M10="","",IF(M10>=Painel!$C$26,"Saudável",IF(M10>=Painel!$C$25,"Atenção","Alerta"))) | O10: =IF(N(C10)=0,"",D10/C10) | P10: =IF(O10="","",IF(O10<=Painel!$C$27,"Saudável",IF(O10<=Painel!$C$28,"Atenção","Alerta")))
B11: Abr/27 | H11: =IF(N(C11)=0,"",C11-D11-E11-F11) | I11: =IF(N(C11)=0,"",MAX(H11,0)/C11) | J11: =IF(I11="","",IF(I11>=Painel!$C$22,"Saudável",IF(I11>0,"Atenção","Alerta"))) | K11: =IF(N(C11)=0,"",F11/C11) | L11: =IF(K11="","",IF(K11<=Painel!$C$23,"Saudável",IF(K11<=Painel!$C$24,"Atenção","Alerta"))) | M11: =IF(OR(N(C11)=0,N(D11)=0),"",G11/D11) | N11: =IF(M11="","",IF(M11>=Painel!$C$26,"Saudável",IF(M11>=Painel!$C$25,"Atenção","Alerta"))) | O11: =IF(N(C11)=0,"",D11/C11) | P11: =IF(O11="","",IF(O11<=Painel!$C$27,"Saudável",IF(O11<=Painel!$C$28,"Atenção","Alerta")))
B12: Mai/27 | H12: =IF(N(C12)=0,"",C12-D12-E12-F12) | I12: =IF(N(C12)=0,"",MAX(H12,0)/C12) | J12: =IF(I12="","",IF(I12>=Painel!$C$22,"Saudável",IF(I12>0,"Atenção","Alerta"))) | K12: =IF(N(C12)=0,"",F12/C12) | L12: =IF(K12="","",IF(K12<=Painel!$C$23,"Saudável",IF(K12<=Painel!$C$24,"Atenção","Alerta"))) | M12: =IF(OR(N(C12)=0,N(D12)=0),"",G12/D12) | N12: =IF(M12="","",IF(M12>=Painel!$C$26,"Saudável",IF(M12>=Painel!$C$25,"Atenção","Alerta"))) | O12: =IF(N(C12)=0,"",D12/C12) | P12: =IF(O12="","",IF(O12<=Painel!$C$27,"Saudável",IF(O12<=Painel!$C$28,"Atenção","Alerta")))
B13: Jun/27 | H13: =IF(N(C13)=0,"",C13-D13-E13-F13) | I13: =IF(N(C13)=0,"",MAX(H13,0)/C13) | J13: =IF(I13="","",IF(I13>=Painel!$C$22,"Saudável",IF(I13>0,"Atenção","Alerta"))) | K13: =IF(N(C13)=0,"",F13/C13) | L13: =IF(K13="","",IF(K13<=Painel!$C$23,"Saudável",IF(K13<=Painel!$C$24,"Atenção","Alerta"))) | M13: =IF(OR(N(C13)=0,N(D13)=0),"",G13/D13) | N13: =IF(M13="","",IF(M13>=Painel!$C$26,"Saudável",IF(M13>=Painel!$C$25,"Atenção","Alerta"))) | O13: =IF(N(C13)=0,"",D13/C13) | P13: =IF(O13="","",IF(O13<=Painel!$C$27,"Saudável",IF(O13<=Painel!$C$28,"Atenção","Alerta")))
B14: Jul/27 | H14: =IF(N(C14)=0,"",C14-D14-E14-F14) | I14: =IF(N(C14)=0,"",MAX(H14,0)/C14) | J14: =IF(I14="","",IF(I14>=Painel!$C$22,"Saudável",IF(I14>0,"Atenção","Alerta"))) | K14: =IF(N(C14)=0,"",F14/C14) | L14: =IF(K14="","",IF(K14<=Painel!$C$23,"Saudável",IF(K14<=Painel!$C$24,"Atenção","Alerta"))) | M14: =IF(OR(N(C14)=0,N(D14)=0),"",G14/D14) | N14: =IF(M14="","",IF(M14>=Painel!$C$26,"Saudável",IF(M14>=Painel!$C$25,"Atenção","Alerta"))) | O14: =IF(N(C14)=0,"",D14/C14) | P14: =IF(O14="","",IF(O14<=Painel!$C$27,"Saudável",IF(O14<=Painel!$C$28,"Atenção","Alerta")))
B15: Ago/27 | H15: =IF(N(C15)=0,"",C15-D15-E15-F15) | I15: =IF(N(C15)=0,"",MAX(H15,0)/C15) | J15: =IF(I15="","",IF(I15>=Painel!$C$22,"Saudável",IF(I15>0,"Atenção","Alerta"))) | K15: =IF(N(C15)=0,"",F15/C15) | L15: =IF(K15="","",IF(K15<=Painel!$C$23,"Saudável",IF(K15<=Painel!$C$24,"Atenção","Alerta"))) | M15: =IF(OR(N(C15)=0,N(D15)=0),"",G15/D15) | N15: =IF(M15="","",IF(M15>=Painel!$C$26,"Saudável",IF(M15>=Painel!$C$25,"Atenção","Alerta"))) | O15: =IF(N(C15)=0,"",D15/C15) | P15: =IF(O15="","",IF(O15<=Painel!$C$27,"Saudável",IF(O15<=Painel!$C$28,"Atenção","Alerta")))
B16: Set/27 | H16: =IF(N(C16)=0,"",C16-D16-E16-F16) | I16: =IF(N(C16)=0,"",MAX(H16,0)/C16) | J16: =IF(I16="","",IF(I16>=Painel!$C$22,"Saudável",IF(I16>0,"Atenção","Alerta"))) | K16: =IF(N(C16)=0,"",F16/C16) | L16: =IF(K16="","",IF(K16<=Painel!$C$23,"Saudável",IF(K16<=Painel!$C$24,"Atenção","Alerta"))) | M16: =IF(OR(N(C16)=0,N(D16)=0),"",G16/D16) | N16: =IF(M16="","",IF(M16>=Painel!$C$26,"Saudável",IF(M16>=Painel!$C$25,"Atenção","Alerta"))) | O16: =IF(N(C16)=0,"",D16/C16) | P16: =IF(O16="","",IF(O16<=Painel!$C$27,"Saudável",IF(O16<=Painel!$C$28,"Atenção","Alerta")))
B17: Out/27 | H17: =IF(N(C17)=0,"",C17-D17-E17-F17) | I17: =IF(N(C17)=0,"",MAX(H17,0)/C17) | J17: =IF(I17="","",IF(I17>=Painel!$C$22,"Saudável",IF(I17>0,"Atenção","Alerta"))) | K17: =IF(N(C17)=0,"",F17/C17) | L17: =IF(K17="","",IF(K17<=Painel!$C$23,"Saudável",IF(K17<=Painel!$C$24,"Atenção","Alerta"))) | M17: =IF(OR(N(C17)=0,N(D17)=0),"",G17/D17) | N17: =IF(M17="","",IF(M17>=Painel!$C$26,"Saudável",IF(M17>=Painel!$C$25,"Atenção","Alerta"))) | O17: =IF(N(C17)=0,"",D17/C17) | P17: =IF(O17="","",IF(O17<=Painel!$C$27,"Saudável",IF(O17<=Painel!$C$28,"Atenção","Alerta")))
